versup/__init__.py
versup/__main__.py
versup/changelog.py
versup/command_line.py
versup/conf_reader.py
versup/custom_cmd_group.py
versup/default_conf.py
versup/file_updater.py
versup/gitops.py
versup/printer.py
versup/script_runner.py
versup/template.py
versup/versioning.py
versup-1.7.1.dist-info/METADATA
versup-1.7.1.dist-info/WHEEL
versup-1.7.1.dist-info/entry_points.txt
versup-1.7.1.dist-info/licenses/LICENSE.txt
versup-1.7.1.dist-info/RECORD
