Metadata-Version: 2.4
Name: versup
Version: 1.7.1
Summary: Version up your project with ease.
Project-URL: repository, https://github.com/Svenito/versup
Author-email: Sven Steinbauer <sven@unlogic.co.uk>
License: The MIT License
License-File: LICENSE.txt
Requires-Python: >=3.10
Requires-Dist: click>=8.1.7
Requires-Dist: gitpython>=3.1.43
Requires-Dist: rich>=13.9.3
Requires-Dist: semver>=3.0.2
